gitlab_mlops/__init__.py
gitlab_mlops/client/__init__.py
gitlab_mlops/client/client.py
gitlab_mlops/experiment/__init__.py
gitlab_mlops/experiment/experiment.py
gitlab_mlops/experiment/run.py
gitlab_mlops/mlflow/__init__.py
gitlab_mlops/mlflow/exceptions.py
gitlab_mlops/model/__init__.py
gitlab_mlops/model/model.py
gitlab_mlops/model/version.py
gitlab_mlops/provider/__init__.py
gitlab_mlops/provider/gcp/__init__.py
gitlab_mlops/provider/gcp/base.py
gitlab_mlops/provider/gcp/storage.py
gitlab_mlops/provider/gcp/vertex.py
gitlab_mlops-0.3.0.dist-info/LICENSE
gitlab_mlops-0.3.0.dist-info/METADATA
gitlab_mlops-0.3.0.dist-info/WHEEL
gitlab_mlops-0.3.0.dist-info/RECORD
