Metadata-Version: 2.3
Name: gitlab-mlops
Version: 0.3.0
Summary: 
Author: GitLab ModelOps
Requires-Python: >=3.11,<4.0
Classifier: Development Status :: 4 - Beta
Classifier: Programming Language :: Python :: 3
Classifier: Programming Language :: Python :: 3.11
Classifier: Programming Language :: Python :: 3.12
Classifier: Programming Language :: Python :: 3.13
Requires-Dist: google-cloud-aiplatform (>=1.80.0,<2.0.0)
Requires-Dist: mlflow (>=2.19.0,<3.0.0)
Requires-Dist: requests (>=2.32.3,<3.0.0)
